caiman/config.py
caiman/deployment.py
caiman/device.py
caiman/installer.py
caiman/loader.py
caiman/manifest.py
caiman/plugins/base.py
caiman/plugins/builder.py
caiman/plugins/core.py
caiman/plugins/deploy.py
caiman/plugins/fs.py
caiman/plugins/installer.py
caiman/plugins/runner.py
caiman/plugins/workspace.py
caiman/proc/__init__.py
caiman/proc/base.py
caiman/proc/device.py
caiman/proc/local.py
caiman/remote/caiman/fs.py
caiman/run.py
caiman/source.py
caiman/task.py
caiman-0.1.0.dist-info/LICENSE
caiman-0.1.0.dist-info/METADATA
caiman-0.1.0.dist-info/WHEEL
caiman-0.1.0.dist-info/entry_points.txt
caiman-0.1.0.dist-info/RECORD
