Metadata-Version: 2.1
Name: caiman
Version: 0.1.0
Summary: A build system for MicroPython projects
Home-page: https://github.com/andreicsp/caiman
License: MIT
Author: Andrei Dumitrache
Author-email: andrei@dumitrache.net
Requires-Python: >=3.9,<4.0
Classifier: License :: OSI Approved :: MIT License
Classifier: Programming Language :: Python :: 3
Classifier: Programming Language :: Python :: 3.9
Classifier: Programming Language :: Python :: 3.10
Classifier: Programming Language :: Python :: 3.11
Classifier: Programming Language :: Python :: 3.12
Requires-Dist: dacite (>=1.8.1,<2.0.0)
Requires-Dist: mpremote (>=1.22.0,<2.0.0)
Requires-Dist: mpy-cross-v6 (>=1.0.1,<2.0.0)
Requires-Dist: pathspec (>=0.12.1,<0.13.0)
Requires-Dist: pyaml (>=23.12.0,<24.0.0)
Project-URL: Repository, https://github.com/andreicsp/caiman
